syngo/__init__.py
syngo/admin.py
syngo/apps.py
syngo/migrations/0001_initial.py
syngo/migrations/__init__.py
syngo/models.py
syngo/templates/syngo/base.html
syngo/templates/syngo/check.html
syngo/templates/syngo/success.html
syngo/tests.py
syngo/urls.py
syngo/views.py
syngo-0.2.0.dist-info/WHEEL
syngo-0.2.0.dist-info/METADATA
syngo-0.2.0.dist-info/RECORD
