Metadata-Version: 2.1
Name: syngo
Version: 0.2.0
Summary: Manage Synapse from Django
Home-page: https://github.com/nim65s/syngo
License: BSD-2-Clause
Author: Guilhem Saurel
Author-email: guilhem.saurel@laas.fr
Requires-Python: >=3.7,<4.0
Classifier: License :: OSI Approved :: BSD License
Classifier: Programming Language :: Python :: 3
Classifier: Programming Language :: Python :: 3.10
Classifier: Programming Language :: Python :: 3.7
Classifier: Programming Language :: Python :: 3.8
Classifier: Programming Language :: Python :: 3.9
Requires-Dist: Django (>=3.2,<4.0)
Requires-Dist: captcha (>=0.4,<0.5)
Requires-Dist: httpx (>=0.23.0,<0.24.0)
Project-URL: Repository, https://github.com/nim65s/syngo.git
Project-URL: changelog, https://github.com/nim65s/syngo/blob/main/CHANGELOG.md
